{
  "date": "2026-05-01",
  "fetched_at": "2026-05-01T22:03:22.343744",
  "zara": {
    "source": "zara.com (official API)",
    "count": 20,
    "items": [
      {
        "rank": 1,
        "name": "ジオメトリック柄バンダナ",
        "price": "¥2,990",
        "image": "https://static.zara.net/assets/public/cd09/fd6b/26104260bfc6/c29dbb2674bf/03921414712-e1/03921414712-e1.jpg?ts=1776676012405&w=563",
        "url": "https://www.zara.com/jp/ja/-p03921414.html"
      },
      {
        "rank": 2,
        "name": "ヘンリーネックニットTシャツ",
        "price": "¥3,950",
        "image": "https://static.zara.net/assets/public/8f6f/859d/be884d0a8167/3b8743ad3b0f/04696430712-e1/04696430712-e1.jpg?ts=1773074388172&w=563",
        "url": "https://www.zara.com/jp/ja/-p04696430.html"
      },
      {
        "rank": 3,
        "name": "アーロン・レヴァイン x ザラ リネン100% ツイルスーツブレザー",
        "price": "¥25,990",
        "image": "https://static.zara.net/assets/public/c89a/135e/634a4e938f92/094cdf59be17/01564312800-e1/01564312800-e1.jpg?ts=1776356390917&w=563",
        "url": "https://www.zara.com/jp/ja/-p01564312.html"
      },
      {
        "rank": 4,
        "name": "ダメージ加工バギーフィットデニムパンツ",
        "price": "¥10,990",
        "image": "https://static.zara.net/assets/public/998d/53e6/f74d4aa9af0a/e1b26906d6be/06688409406-e1/06688409406-e1.jpg?ts=1776939570015&w=563",
        "url": "https://www.zara.com/jp/ja/-p06688409.html"
      },
      {
        "rank": 5,
        "name": "サテン リラックスフィットシャツ",
        "price": "¥3,950",
        "image": "https://static.zara.net/assets/public/b5f7/2308/50c34a15b822/e8de67c803ca/04423209802-e1/04423209802-e1.jpg?ts=1772094859437&w=563",
        "url": "https://www.zara.com/jp/ja/-p04423209.html"
      },
      {
        "rank": 6,
        "name": "バギーフィットデニムパンツ",
        "price": "¥6,590",
        "image": "https://static.zara.net/assets/public/e38f/e7fc/d2394dfa87f2/79d2ba5569ea/04048407445-e1/04048407445-e1.jpg?ts=1770296424371&w=563",
        "url": "https://www.zara.com/jp/ja/-p04048407.html"
      },
      {
        "rank": 7,
        "name": "ダメージ加工バギーフィットデニムパンツ",
        "price": "¥6,590",
        "image": "https://static.zara.net/assets/public/0cb8/a211/90d94ee6a379/f485effa59e1/04048407400-e1/04048407400-e1.jpg?ts=1770655723876&w=563",
        "url": "https://www.zara.com/jp/ja/-p04048407.html"
      },
      {
        "rank": 8,
        "name": "テクニカルマルチポケットバッグ",
        "price": "¥3,950",
        "image": "https://static.zara.net/assets/public/39a7/5aa3/0c2e4078912a/aa5ac7e541d8/13305720800-e1/13305720800-e1.jpg?ts=1761642727912&w=563",
        "url": "https://www.zara.com/jp/ja/-p13305720.html"
      },
      {
        "rank": 9,
        "name": "ヘンリーネックワッフルニットTシャツ",
        "price": "¥6,590",
        "image": "https://static.zara.net/assets/public/00c0/5127/7bde4cd38e43/00e0213e837d/00526444898-e1/00526444898-e1.jpg?ts=1772093314414&w=563",
        "url": "https://www.zara.com/jp/ja/-p00526444.html"
      },
      {
        "rank": 10,
        "name": "ヘンリーネックTシャツ",
        "price": "¥5,290",
        "image": "https://static.zara.net/assets/public/fef0/7359/46844f13b0f6/d7c01da09a5a/00526403800-e1/00526403800-e1.jpg?ts=1765813441506&w=563",
        "url": "https://www.zara.com/jp/ja/-p00526403.html"
      },
      {
        "rank": 11,
        "name": "SILVER MAN GOLD オードトワレ 2X100 ML (3.4 FL.OZ)",
        "price": "¥2,390",
        "image": "https://static.zara.net/assets/public/b4ea/b07a/bcaf4fb598d3/90cd3b99e7bd/20210012999-e1/20210012999-e1.jpg?ts=1765540099504&w=563",
        "url": "https://www.zara.com/jp/ja/-p20210012.html"
      },
      {
        "rank": 12,
        "name": "リラックスフィット100%リネンシャツ",
        "price": "¥7,990",
        "image": "https://static.zara.net/assets/public/6b64/f6cf/52cc4dc395b2/bca2799a83ee/05070904052-e1/05070904052-e1.jpg?ts=1766058285794&w=563",
        "url": "https://www.zara.com/jp/ja/-p05070904.html"
      },
      {
        "rank": 13,
        "name": "バギーフィットデニムパンツ",
        "price": "¥6,590",
        "image": "https://static.zara.net/assets/public/4187/008a/f04a4e9e925e/7f5a8d9a9d41/04806409800-e1/04806409800-e1.jpg?ts=1770296415989&w=563",
        "url": "https://www.zara.com/jp/ja/-p04048407.html"
      },
      {
        "rank": 14,
        "name": "ニットヘンリーネックＴシャツ",
        "price": "¥3,950",
        "image": "https://static.zara.net/assets/public/d21a/9c77/f18540f6b239/f89218b93d70/04696430505-e1/04696430505-e1.jpg?ts=1773074395331&w=563",
        "url": "https://www.zara.com/jp/ja/-p04696430.html"
      },
      {
        "rank": 15,
        "name": "ウォッシュドストライプ柄リラックスフィットシャツ",
        "price": "¥8,590",
        "image": "https://static.zara.net/assets/public/a40e/dabf/770a437dabf0/2cb1a4fed4ef/07545447400-e1/07545447400-e1.jpg?ts=1776675963698&w=563",
        "url": "https://www.zara.com/jp/ja/-p07545447.html"
      },
      {
        "rank": 16,
        "name": "フレアフィットジーンズ",
        "price": "¥8,590",
        "image": "https://static.zara.net/assets/public/2c8d/31ec/be4b4a2d9af7/c49480fa5e53/00840373800-e1/00840373800-e1.jpg?ts=1770053689644&w=563",
        "url": "https://www.zara.com/jp/ja/-p00840353.html"
      },
      {
        "rank": 17,
        "name": "ベーシックスリムフィットTシャツ /01",
        "price": "¥1,990",
        "image": "https://static.zara.net/assets/public/8450/47b1/886245b8a7e6/fca1014ee004/05584361800-e1/05584361800-e1.jpg?ts=1756290169986&w=563",
        "url": "https://www.zara.com/jp/ja/-p05584401.html"
      },
      {
        "rank": 18,
        "name": "バギーフィットデニムパンツ",
        "price": "¥6,590",
        "image": "https://static.zara.net/assets/public/8afd/9c95/802a4eec85d1/3dcc42b04d8d/00840457427-e1/00840457427-e1.jpg?ts=1770291402850&w=563",
        "url": "https://www.zara.com/jp/ja/-p04048407.html"
      },
      {
        "rank": 19,
        "name": "リラックスフィットピンストライプ柄ジョーツ",
        "price": "¥7,990",
        "image": "https://static.zara.net/assets/public/aeb4/6630/35a149e99260/c41cf2fb8562/04048420712-e1/04048420712-e1.jpg?ts=1775743391548&w=563",
        "url": "https://www.zara.com/jp/ja/-p04048420.html"
      },
      {
        "rank": 20,
        "name": "リネン＆コットン製ダブルブレストブレザー",
        "price": "¥22,990",
        "image": "https://static.zara.net/assets/public/27f7/457d/ede9424f975f/47bb45b8f93e/04552594405-e1/04552594405-e1.jpg?ts=1775731509796&w=563",
        "url": "https://www.zara.com/jp/ja/-p04552594.html"
      }
    ]
  },
  "musinsa": {
    "source": "global.musinsa.com/jp",
    "count": 18,
    "items": [
      {
        "rank": 1,
        "name": "Deep One Tuck Sweat Shorts [Black]",
        "brand": "XERO",
        "price": "¥3,596",
        "image": "https://image.msscdn.net/thumbnails/images/goods_img/20210428/1926034/1926034_1_big.jpg",
        "url": "https://global.musinsa.com/jp/goods/1926034"
      },
      {
        "rank": 2,
        "name": "[ソサーピック] アンシンバルーンティント 16種",
        "brand": "ODDTYPE",
        "price": "¥2,225",
        "image": "https://image.msscdn.net/thumbnails/global_images/goods_img/20240220/3882622/3882622_17687842869849_big.jpg",
        "url": "https://global.musinsa.com/jp/goods/3882622"
      },
      {
        "rank": 3,
        "name": "ワンタッチワイドスウェットパンツブラック",
        "brand": "GAKKAI UNIONS",
        "price": "¥2,921",
        "image": "https://image.msscdn.net/thumbnails/images/goods_img/20210906/2112061/2112061_17459952841713_big.jpg",
        "url": "https://global.musinsa.com/jp/goods/2112061"
      },
      {
        "rank": 4,
        "name": "[ON]ウォッシャブルストライプヘンリーネック半袖ニット - 2カラー",
        "brand": "MINDBRIDGE",
        "price": "¥5,764",
        "image": "https://image.msscdn.net/thumbnails/images/goods_img/20260310/6109259/6109259_17775277201861_big.jpg",
        "url": "https://global.musinsa.com/jp/goods/6109259"
      },
      {
        "rank": 5,
        "name": "ワンタッチワイドスウェットパンツグレー",
        "brand": "GAKKAI UNIONS",
        "price": "¥2,921",
        "image": "https://image.msscdn.net/thumbnails/images/goods_img/20210906/2112059/2112059_17473624399256_big.jpg",
        "url": "https://global.musinsa.com/jp/goods/2112059"
      },
      {
        "rank": 6,
        "name": "リアルワイドヒドゥンバンディングスラックス[ブラック]",
        "brand": "MUSINSA STANDARD",
        "price": "¥4,448",
        "image": "https://image.msscdn.net/thumbnails/images/goods_img/20190927/1168922/1168922_17569508760902_big.jpg",
        "url": "https://global.musinsa.com/jp/goods/1168922"
      },
      {
        "rank": 7,
        "name": "[シティレジャー] シアウィンドブレーカー ジャケット [ブラック]",
        "brand": "MUSINSA STANDARD",
        "price": "¥5,159",
        "image": "https://image.msscdn.net/thumbnails/images/goods_img/20240112/3793565/3793565_17738965169888_big.jpg",
        "url": "https://global.musinsa.com/jp/goods/3793565"
      },
      {
        "rank": 8,
        "name": "Cencel See-Through Classic Shirt - 6COL",
        "brand": "VIVACIOUS",
        "price": "¥7,362",
        "image": "https://image.msscdn.net/thumbnails/images/goods_img/20240510/4121422/4121422_17162812146013_big.jpg",
        "url": "https://global.musinsa.com/jp/goods/4121422"
      },
      {
        "rank": 9,
        "name": "[アトリエスタンダード] ネチュラルリンクルスカート_2COLOR(WB6SK05)",
        "brand": "WEDNESDAYOASIS FOR WOMEN",
        "price": "¥4,944",
        "image": "https://image.msscdn.net/thumbnails/images/goods_img/20260410/6290152/6290152_17770077487465_big.jpg",
        "url": "https://global.musinsa.com/jp/goods/6290152"
      },
      {
        "rank": 10,
        "name": "[BEST SELLER] PARACHUTE CARGO PANTS BLACK",
        "brand": "ASIF CALIE",
        "price": "¥13,023",
        "image": "https://image.msscdn.net/thumbnails/global_images/goods_img/20230531/3337501/3337501_17731066250031_big.jpg",
        "url": "https://global.musinsa.com/jp/goods/3337501"
      },
      {
        "rank": 11,
        "name": "セミワイド隠しバンディングスラックス[ブラック]",
        "brand": "MUSINSA STANDARD",
        "price": "¥5,111",
        "image": "https://image.msscdn.net/thumbnails/images/goods_img/20190910/1149329/1149329_17775152531848_big.jpg",
        "url": "https://global.musinsa.com/jp/goods/1149329"
      },
      {
        "rank": 12,
        "name": "ポストセミクロップ半袖Tシャツ[グレーメランジ]",
        "brand": "SEW-B",
        "price": "¥2,648",
        "image": "https://image.msscdn.net/thumbnails/images/goods_img/20260211/6013713/6013713_17708905341532_big.png",
        "url": "https://global.musinsa.com/jp/goods/6013713"
      },
      {
        "rank": 13,
        "name": "[クールタンダード] ワイドデニムパンツ [スカイブルー]",
        "brand": "MUSINSA STANDARD",
        "price": "¥6,573",
        "image": "https://image.msscdn.net/thumbnails/images/goods_img/20230201/3051697/3051697_16901546810890_big.jpg",
        "url": "https://global.musinsa.com/jp/goods/3051697"
      },
      {
        "rank": 14,
        "name": "ヘビーウェイトオーバーサイズフード付きスウェットジップアップ[ブラック]",
        "brand": "MUSINSA STANDARD",
        "price": "¥6,966",
        "image": "https://image.msscdn.net/thumbnails/images/goods_img/20201012/1642914/1642914_17526403710213_big.jpg",
        "url": "https://global.musinsa.com/jp/goods/1642914"
      },
      {
        "rank": 15,
        "name": "女性用軽量ストレート隠しバンディングスラックス[ブラック]",
        "brand": "MUSINSA STANDARD WOMAN",
        "price": "¥2,372",
        "image": "https://image.msscdn.net/thumbnails/images/goods_img/20210511/1945319/1945319_2_big.jpg",
        "url": "https://global.musinsa.com/jp/goods/1945319"
      },
      {
        "rank": 16,
        "name": "TCM apo T (purple)",
        "brand": "THE COLDEST MOMENT",
        "price": "¥4,500",
        "image": "https://image.msscdn.net/thumbnails/images/goods_img/20260312/6120868/6120868_17756153604516_big.jpg",
        "url": "https://global.musinsa.com/jp/goods/6120868"
      },
      {
        "rank": 17,
        "name": "DOODLE HEART HALF T WHITE GREYISH BLUE",
        "brand": "MAISON MINED",
        "price": "¥4,309",
        "image": "https://image.msscdn.net/thumbnails/images/goods_img/20230525/3325842/3325842_17760653699611_big.jpg",
        "url": "https://global.musinsa.com/jp/goods/3325842"
      },
      {
        "rank": 18,
        "name": "ウィメンズパラシュートパンツ [ガンメタル]",
        "brand": "MUSINSA STANDARD WOMAN",
        "price": "¥3,974",
        "image": "https://image.msscdn.net/thumbnails/images/goods_img/20221209/2978126/2978126_17677824398044_big.jpg",
        "url": "https://global.musinsa.com/jp/goods/2978126"
      }
    ]
  },
  "buyma": {
    "source": "buyma.com",
    "count": 20,
    "items": [
      {
        "rank": 1,
        "name": "★SATUR★Waffle Henry Neck T-shirt",
        "brand": "SATUR",
        "price": "¥6,980",
        "image": "https://cdn-images.buyma.com/imgdata/item/260313/0129253861/768569611/210.jpg",
        "url": "https://www.buyma.com/item/129253861/"
      },
      {
        "rank": 2,
        "name": "新色入荷！【NIKE】最新 AIR FORCE 1 \"White Croc\" 送料関税無料",
        "brand": "Nike",
        "price": "¥30,000",
        "image": "https://cdn-images.buyma.com/imgdata/item/260415/0130737123/779480100/210.jpg",
        "url": "https://www.buyma.com/item/130737123/"
      },
      {
        "rank": 3,
        "name": "BALENCIAGA    BB0096S 001 (BB0096S 001)",
        "brand": "BALENCIAGA",
        "price": "¥39,180",
        "image": "https://cdn-images.buyma.com/imgdata/item/260317/0129387106/769613727/210.jpg",
        "url": "https://www.buyma.com/item/129387106/"
      },
      {
        "rank": 4,
        "name": "【Thug Club】TC Basic T-shirt◆",
        "brand": "Thug Club",
        "price": "¥11,900",
        "image": "https://cdn-images.buyma.com/imgdata/item/240425/0106076859/780757197/210.jpg",
        "url": "https://www.buyma.com/item/106076859/"
      },
      {
        "rank": 5,
        "name": "[ラルフローレン] パックTシャツ スリムフィット 3枚セット",
        "brand": "Ralph Lauren",
        "price": "¥14,400",
        "image": "https://cdn-images.buyma.com/imgdata/item/250809/0121208078/777619489/210.jpg",
        "url": "https://www.buyma.com/item/121208078/"
      },
      {
        "rank": 6,
        "name": "【国内即発】AMI ALEXANDRE MATTIUSSI コットン Tシャツ",
        "brand": "AMI PARIS",
        "price": "¥17,955",
        "image": "https://cdn-images.buyma.com/imgdata/item/250306/0116234650/769398632/210.jpg",
        "url": "https://www.buyma.com/item/116234650/"
      },
      {
        "rank": 7,
        "name": "【Thug Club】Basic T-shirt◆　Ver.２　希少商品",
        "brand": "Thug Club",
        "price": "¥13,980",
        "image": "https://cdn-images.buyma.com/imgdata/item/240716/0108756568/682633167/210.jpg",
        "url": "https://www.buyma.com/item/108756568/"
      },
      {
        "rank": 8,
        "name": "1-3日着/追跡【即発】COMME des GARCONS メンズ カットソー",
        "brand": "COMME des GARCONS",
        "price": "¥8,440",
        "image": "https://cdn-images.buyma.com/imgdata/item/240201/0103284897/597430075/210.jpg",
        "url": "https://www.buyma.com/item/103284897/"
      },
      {
        "rank": 9,
        "name": "★SATUR★Small Logo Hood Zip-up",
        "brand": "SATUR",
        "price": "¥8,791",
        "image": "https://cdn-images.buyma.com/imgdata/item/260123/0127089297/752378126/210.jpg",
        "url": "https://www.buyma.com/item/127089297/"
      },
      {
        "rank": 10,
        "name": "Adidas Originals Three-Stripe Overfit Unisex Sweatshirt Blue",
        "brand": "adidas",
        "price": "¥12,985",
        "image": "https://cdn-images.buyma.com/imgdata/item/260225/0128454275/762652226/210.jpg",
        "url": "https://www.buyma.com/item/128454275/"
      },
      {
        "rank": 11,
        "name": "★SATUR★Essential Lawton Track Zip-up Jacket",
        "brand": "SATUR",
        "price": "¥8,420",
        "image": "https://cdn-images.buyma.com/imgdata/item/260123/0127086480/752357772/210.jpg",
        "url": "https://www.buyma.com/item/127086480/"
      },
      {
        "rank": 12,
        "name": "★関税送料込み★ Maison margiela 二つ折り財布 S56UI0140P4455",
        "brand": "Maison Margiela",
        "price": "¥47,965",
        "image": "https://cdn-images.buyma.com/imgdata/item/230105/0090661791/625138024/210.jpg",
        "url": "https://www.buyma.com/item/90661791/"
      },
      {
        "rank": 13,
        "name": "COMME des GARCONS メンズ ハートロゴ 長袖 Tシャツ",
        "brand": "COMME des GARCONS",
        "price": "¥8,840",
        "image": "https://cdn-images.buyma.com/imgdata/item/191011/0048042541/571973137/210.jpg",
        "url": "https://www.buyma.com/item/48042541/"
      },
      {
        "rank": 14,
        "name": "★AMI DE COEUR SMALL HEART T-SHIRT ロゴ Tシャツ",
        "brand": "AMI PARIS",
        "price": "¥16,247",
        "image": "https://cdn-images.buyma.com/imgdata/item/250610/0119224402/702401017/210.jpg",
        "url": "https://www.buyma.com/item/119224402/"
      },
      {
        "rank": 15,
        "name": "【国内即発】DIESEL T-ADJUST-OD オーガニックコットンTシャツ",
        "brand": "DIESEL",
        "price": "¥9,975",
        "image": "https://cdn-images.buyma.com/imgdata/item/250213/0115573509/782320717/210.jpg",
        "url": "https://www.buyma.com/item/115573509/"
      },
      {
        "rank": 16,
        "name": "[ノースフェイス]ELECTRON スリングバッグ★新作・26SS★男女★",
        "brand": "THE NORTH FACE",
        "price": "¥8,593",
        "image": "https://cdn-images.buyma.com/imgdata/item/260203/0127512949/765834142/210.jpg",
        "url": "https://www.buyma.com/item/127512949/"
      },
      {
        "rank": 17,
        "name": "【STONE ISLAND】ストーンアイランド ロゴ ワッペン スウェット",
        "brand": "STONE ISLAND",
        "price": "¥39,600",
        "image": "https://cdn-images.buyma.com/imgdata/item/251105/0124514771/736588306/210.jpg",
        "url": "https://www.buyma.com/item/124514771/"
      },
      {
        "rank": 18,
        "name": "【NIKE】快適軽量！Air Force 1 Flyknit 2.0　AV3042-100",
        "brand": "Nike",
        "price": "¥26,400",
        "image": "https://cdn-images.buyma.com/imgdata/item/240917/0110610767/645159362/210.jpg",
        "url": "https://www.buyma.com/item/110610767/"
      },
      {
        "rank": 19,
        "name": "関税込み♪【POLO RALPH LAUREN】Tシャツ&ショーツ ★上下セット",
        "brand": "POLO RALPH LAUREN",
        "price": "¥39,480",
        "image": "https://cdn-images.buyma.com/imgdata/item/260312/0129200166/768203632/210.jpg",
        "url": "https://www.buyma.com/item/129200166/"
      },
      {
        "rank": 20,
        "name": "VERSACE ヴェルサーチ クルーネック半袖Tシャツ AUU01005",
        "brand": "VERSACE",
        "price": "¥6,732",
        "image": "https://cdn-images.buyma.com/imgdata/item/250519/0118565004/697960902/210.jpg",
        "url": "https://www.buyma.com/item/118565004/"
      }
    ]
  },
  "stockx": {
    "source": "stockx.com",
    "count": 20,
    "items": [
      {
        "rank": 1,
        "name": "adidas CTT Chinese Track Top 3.1 Gender Neutral Jacket (Asia Sizing) Grey Blue",
        "price": "$170",
        "image": "https://images.stockx.com/images/Adidas-CTT-Chinese-Track-Top-31-Gender-Neutral-Jacket-Asia-Sizing-Dark-Grey.jpg?fit=fill&bg=FFFFFF&w=140&h=75&q=60&dpr=1&trim=color&updated_at=1765347012",
        "url": "https://stockx.com/ja-jp/adidas-ctt-chinese-track-top-31-gender-neutral-jacket-asia-sizing-dark-grey"
      },
      {
        "rank": 2,
        "name": "Nike FC Barcelona Re-Issue 2005/06 Ronaldinho #10 Home Jersey Multicolor",
        "price": "$142",
        "image": "https://images.stockx.com/images/Nike-FC-Barcelona-2005-06-Ronaldinho-10-Home-Jersey-Multicolor.jpg?fit=fill&bg=FFFFFF&w=140&h=75&q=60&dpr=1&trim=color&updated_at=1772580552",
        "url": "https://stockx.com/ja-jp/nike-fc-barcelona-2005-06-ronaldinho-10-home-jersey-multicolor"
      },
      {
        "rank": 3,
        "name": "Supreme MM6 Maison Margiela Box Logo Zip Up Hooded Sweatshirt Navy",
        "price": "$640",
        "image": "https://images.stockx.com/images/Supreme-MM6-Maison-Margiela-Box-Logo-Zip-Up-Hooded-Sweatshirt-Navy-Product.jpg?fit=fill&bg=FFFFFF&w=140&h=75&q=60&dpr=1&trim=color&updated_at=1773930781",
        "url": "https://stockx.com/ja-jp/supreme-mm6-maison-margiela-box-logo-zip-up-hooded-sweatshirt-navy"
      },
      {
        "rank": 4,
        "name": "Jordan 1 Retro High Virgil Abloh Archive Alaska",
        "price": "$330",
        "image": "https://images.stockx.com/images/Air-Jordan-1-Retro-High-Off-White-Alaska-Product.jpg?fit=fill&bg=FFFFFF&w=140&h=75&q=60&dpr=1&trim=color&updated_at=1774463315",
        "url": "https://stockx.com/ja-jp/air-jordan-1-retro-high-virgil-abloh-archive-alaska"
      },
      {
        "rank": 5,
        "name": "Jordan 5 Retro White Metallic (2026)",
        "price": "$161",
        "image": "https://images.stockx.com/images/Air-Jordan-5-Retro-White-Metallic-2026-Product.jpg?fit=fill&bg=FFFFFF&w=140&h=75&q=60&dpr=1&trim=color&updated_at=1775837191",
        "url": "https://stockx.com/ja-jp/air-jordan-5-retro-white-metallic-2026"
      },
      {
        "rank": 6,
        "name": "Supreme Grim Reaper Tee Black",
        "price": "$60",
        "image": "https://images.stockx.com/images/Supreme-Grim-Reaper-Tee-Black-Product.jpg?fit=fill&bg=FFFFFF&w=140&h=75&q=60&dpr=1&trim=color&updated_at=1775747347",
        "url": "https://stockx.com/ja-jp/supreme-grim-reaper-tee-black"
      },
      {
        "rank": 7,
        "name": "Supreme Ghostface Arc Hooded Sweatshirt Black",
        "price": "$254",
        "image": "https://images.stockx.com/images/Supreme-Ghostface-Arc-Hooded-Sweatshirt-Black-Product.jpg?fit=fill&bg=FFFFFF&w=140&h=75&q=60&dpr=1&trim=color&updated_at=1777560540",
        "url": "https://stockx.com/ja-jp/supreme-ghostface-arc-hooded-sweatshirt-black"
      },
      {
        "rank": 8,
        "name": "Swatch x Omega Bioceramic Mission To Earthphase Moonshine Gold \"Cold Moon\" SO33W701L",
        "price": "$565",
        "image": "https://images.stockx.com/images/Swatch-x-Omega-Bioceramic-Mission-To-Earthphase-Moonshine-Gold-Cold-Moon-SO33W701L-White.jpg?fit=fill&bg=FFFFFF&w=140&h=75&q=60&dpr=1&trim=color&updated_at=1766389309",
        "url": "https://stockx.com/ja-jp/swatch-x-omega-bioceramic-mission-to-earthphase-moonshine-gold-cold-moon-so33w701l-white"
      },
      {
        "rank": 9,
        "name": "Gymshark Onyx 5.0 Seamless Hoodie Black/Onyx Grey",
        "price": "$86",
        "image": "https://images.stockx.com/images/Gymshark-Onyx-50-Seamless-Hoodie-Black-Onyx-Grey-v2.jpg?fit=fill&bg=FFFFFF&w=140&h=75&q=60&dpr=1&trim=color&updated_at=1774891180",
        "url": "https://stockx.com/ja-jp/gymshark-onyx-50-seamless-hoodie-black-onyx-grey"
      },
      {
        "rank": 10,
        "name": "Jordan 6 Retro Cap and Gown",
        "price": "$164",
        "image": "https://images.stockx.com/images/Air-Jordan-6-Retro-Cap-and-Gown-Product.jpg?fit=fill&bg=FFFFFF&w=140&h=75&q=60&dpr=1&trim=color&updated_at=1776965551",
        "url": "https://stockx.com/ja-jp/air-jordan-6-retro-cap-and-gown"
      },
      {
        "rank": 11,
        "name": "Nike Mind 001 Slide Team Red University Red",
        "price": "$177",
        "image": "https://images.stockx.com/images/Nike-Mind-001-Slide-Team-Red-University-Red-Product.jpg?fit=fill&bg=FFFFFF&w=140&h=75&q=60&dpr=1&trim=color&updated_at=1775837656",
        "url": "https://stockx.com/ja-jp/nike-mind-001-slide-team-red-university-red"
      },
      {
        "rank": 12,
        "name": "adidas x BAPE Relaxed Fit Track Camo Shark Full Zip Hoodie Green",
        "price": "$250",
        "image": "https://images.stockx.com/images/adidas-x-BAPE-Relaxed-Fit-Track-Camo-Shark-Full-Zip-Hoodie-Green.jpg?fit=fill&bg=FFFFFF&w=140&h=75&q=60&dpr=1&trim=color&updated_at=1770281241",
        "url": "https://stockx.com/ja-jp/adidas-x-bape-relaxed-fit-track-camo-shark-full-zip-hoodie-green"
      },
      {
        "rank": 13,
        "name": "Supreme MM6 Maison Margiela Cotton Football Jersey Black",
        "price": "$265",
        "image": "https://images.stockx.com/images/Supreme-MM6-Maison-Margiela-Cotton-Football-Jersey-Black-Product.jpg?fit=fill&bg=FFFFFF&w=140&h=75&q=60&dpr=1&trim=color&updated_at=1773930779",
        "url": "https://stockx.com/ja-jp/supreme-mm6-maison-margiela-cotton-football-jersey-black"
      },
      {
        "rank": 14,
        "name": "Supreme Fiji Soccer Jersey Multicolor",
        "price": "$178",
        "image": "https://images.stockx.com/images/Supreme-Fiji-Soccer-Jersey-Multicolor-Product.jpg?fit=fill&bg=FFFFFF&w=140&h=75&q=60&dpr=1&trim=color&updated_at=1776956547",
        "url": "https://stockx.com/ja-jp/supreme-fiji-soccer-jersey-multicolor"
      },
      {
        "rank": 15,
        "name": "Supreme The Great China Wall Dragon Polo Black",
        "price": "$178",
        "image": "https://images.stockx.com/images/Supreme-The-Great-China-Wall-Dragon-Polo-Black-Product.jpg?fit=fill&bg=FFFFFF&w=140&h=75&q=60&dpr=1&trim=color&updated_at=1775143024",
        "url": "https://stockx.com/ja-jp/supreme-the-great-china-wall-dragon-polo-black"
      },
      {
        "rank": 16,
        "name": "Sp5der Punk V2 Hoodie Cyan",
        "price": "$200",
        "image": "https://images.stockx.com/images/Sp5der-Punk-V2-Hoodie-Cyan.jpg?fit=fill&bg=FFFFFF&w=140&h=75&q=60&dpr=1&trim=color&updated_at=1755613102",
        "url": "https://stockx.com/ja-jp/sp5der-punk-v2-hoodie-cyan"
      },
      {
        "rank": 17,
        "name": "Jordan 1 Retro Low OG Banned",
        "price": "$140",
        "image": "https://images.stockx.com/images/Air-Jordan-1-Retro-Low-OG-Banned-Product.jpg?fit=fill&bg=FFFFFF&w=140&h=75&q=60&dpr=1&trim=color&updated_at=1776442770",
        "url": "https://stockx.com/ja-jp/air-jordan-1-retro-low-og-banned"
      },
      {
        "rank": 18,
        "name": "Supreme Flag Double Knee Painter Pant Black",
        "price": "$450",
        "image": "https://images.stockx.com/images/Supreme-Flag-Double-Knee-Painter-Pant-Black-Product.jpg?fit=fill&bg=FFFFFF&w=140&h=75&q=60&dpr=1&trim=color&updated_at=1774536173",
        "url": "https://stockx.com/ja-jp/supreme-flag-double-knee-painter-pant-black"
      },
      {
        "rank": 19,
        "name": "Palace x Nike Font Swoosh T-shirt Charcoal",
        "price": "$137",
        "image": "https://images.stockx.com/images/Palace-x-Nike-Font-Swoosh-T-shirt-Charcoal.jpg?fit=fill&bg=FFFFFF&w=140&h=75&q=60&dpr=1&trim=color&updated_at=1775841961",
        "url": "https://stockx.com/ja-jp/palace-x-nike-font-swoosh-t-shirt-charcoal"
      },
      {
        "rank": 20,
        "name": "Nike Air Max 90 Coconut Milk Deep Royal Blue",
        "price": "$191",
        "image": "https://images.stockx.com/images/Nike-Air-Max-90-Coconut-Milk-Deep-Royal-Blue.jpg?fit=fill&bg=FFFFFF&w=140&h=75&q=60&dpr=1&trim=color&updated_at=1776264689",
        "url": "https://stockx.com/ja-jp/nike-air-max-90-coconut-milk-deep-royal-blue"
      }
    ]
  },
  "ssense": {
    "source": "ssense.com",
    "count": 20,
    "items": [
      {
        "rank": 1,
        "name": "ブラック Pajama ラウンジパンツ",
        "brand": "Entire Studios",
        "price": "¥37,000",
        "image": "https://res.cloudinary.com/ssenseweb/image/upload/__IMAGE_PARAMS__/261940M190002_1.jpg",
        "url": "https://www.ssense.com/ja-jp/men/product/19107741"
      },
      {
        "rank": 2,
        "name": "ブラック Sponge プルオーバー スウェットシャツ",
        "brand": "sacai",
        "price": "¥49,500",
        "image": "https://res.cloudinary.com/ssenseweb/image/upload/__IMAGE_PARAMS__/261445M204005_1.jpg",
        "url": "https://www.ssense.com/ja-jp/men/product/18984731"
      },
      {
        "rank": 3,
        "name": "ブラック Align MX トラウザーズ",
        "brand": "Veilance",
        "price": "¥38,000",
        "image": "https://res.cloudinary.com/ssenseweb/image/upload/__IMAGE_PARAMS__/252494M191008_1.jpg",
        "url": "https://www.ssense.com/ja-jp/men/product/17526621"
      },
      {
        "rank": 4,
        "name": "ベージュ 半袖 ニットポロシャツ",
        "brand": "Entire Studios",
        "price": "¥22,400",
        "image": "https://res.cloudinary.com/ssenseweb/image/upload/__IMAGE_PARAMS__/252940M212002_1.jpg",
        "url": "https://www.ssense.com/ja-jp/men/product/18231371"
      },
      {
        "rank": 5,
        "name": "ブラック Signature 90s 半袖Tシャツ",
        "brand": "Fear of God ESSENTIALS",
        "price": "¥18,000",
        "image": "https://res.cloudinary.com/ssenseweb/image/upload/__IMAGE_PARAMS__/261161M213061_1.jpg",
        "url": "https://www.ssense.com/ja-jp/men/product/18989651"
      },
      {
        "rank": 6,
        "name": "グリーン Evening ポロ カーディガン",
        "brand": "OUR LEGACY",
        "price": "¥73,500",
        "image": "https://res.cloudinary.com/ssenseweb/image/upload/__IMAGE_PARAMS__/252803M200007_1.jpg",
        "url": "https://www.ssense.com/ja-jp/men/product/18156591"
      },
      {
        "rank": 7,
        "name": "SSENSE限定 シルバー Taekwondo F50 スニーカー",
        "brand": "adidas Originals",
        "price": "¥28,500",
        "image": "https://res.cloudinary.com/ssenseweb/image/upload/__IMAGE_PARAMS__/252751M237228_1.jpg",
        "url": "https://www.ssense.com/ja-jp/men/product/18489181"
      },
      {
        "rank": 8,
        "name": "Super Slim Ladon ネックレス",
        "brand": "OUR LEGACY",
        "price": "¥25,000",
        "image": "https://res.cloudinary.com/ssenseweb/image/upload/__IMAGE_PARAMS__/261803M145003_1.jpg",
        "url": "https://www.ssense.com/ja-jp/men/product/18883061"
      },
      {
        "rank": 9,
        "name": "ブラック Gem ジーンズ",
        "brand": "Entire Studios",
        "price": "¥35,900",
        "image": "https://res.cloudinary.com/ssenseweb/image/upload/__IMAGE_PARAMS__/252940M186004_1.jpg",
        "url": "https://www.ssense.com/ja-jp/men/product/18234411"
      },
      {
        "rank": 10,
        "name": "ブルー Third Cut ジーンズ",
        "brand": "OUR LEGACY",
        "price": "¥82,000",
        "image": "https://res.cloudinary.com/ssenseweb/image/upload/__IMAGE_PARAMS__/261803M186007_1.jpg",
        "url": "https://www.ssense.com/ja-jp/men/product/18882871"
      },
      {
        "rank": 11,
        "name": "ブラック Cut Peak キャップ",
        "brand": "Martine Rose",
        "price": "¥49,000",
        "image": "https://res.cloudinary.com/ssenseweb/image/upload/__IMAGE_PARAMS__/261892M139000_1.jpg",
        "url": "https://www.ssense.com/ja-jp/men/product/18887211"
      },
      {
        "rank": 12,
        "name": "ブラウン Soft Tab Studs Dots カードケース",
        "brand": "LEMAIRE",
        "price": "¥43,000",
        "image": "https://res.cloudinary.com/ssenseweb/image/upload/__IMAGE_PARAMS__/261646M163005_1.jpg",
        "url": "https://www.ssense.com/ja-jp/men/product/18939721"
      },
      {
        "rank": 13,
        "name": "ブラック Replica スニーカー",
        "brand": "Maison Margiela",
        "price": "¥142,500",
        "image": "https://res.cloudinary.com/ssenseweb/image/upload/__IMAGE_PARAMS__/252168M237027_1.jpg",
        "url": "https://www.ssense.com/ja-jp/men/product/18197931"
      },
      {
        "rank": 14,
        "name": "ブラック Daddy-O サングラス",
        "brand": "Ray-Ban",
        "price": "¥22,000",
        "image": "https://res.cloudinary.com/ssenseweb/image/upload/__IMAGE_PARAMS__/261718M134035_1.jpg",
        "url": "https://www.ssense.com/ja-jp/men/product/19206031"
      },
      {
        "rank": 15,
        "name": "ブラック Temple Sneaks スニーカー",
        "brand": "Rick Owens",
        "price": "¥174,000",
        "image": "https://res.cloudinary.com/ssenseweb/image/upload/__IMAGE_PARAMS__/261232M236039_1.jpg",
        "url": "https://www.ssense.com/ja-jp/men/product/18660391"
      },
      {
        "rank": 16,
        "name": "グレー MA Core Logo フーディ",
        "brand": "AMIRI",
        "price": "¥126,500",
        "image": "https://res.cloudinary.com/ssenseweb/image/upload/__IMAGE_PARAMS__/252886M202015_1.jpg",
        "url": "https://www.ssense.com/ja-jp/men/product/17893831"
      },
      {
        "rank": 17,
        "name": "Concordians Strobe Neck Band チョーカー",
        "brand": "Rick Owens DRKSHDW",
        "price": "¥24,200",
        "image": "https://res.cloudinary.com/ssenseweb/image/upload/__IMAGE_PARAMS__/252126M145002_1.jpg",
        "url": "https://www.ssense.com/ja-jp/men/product/18309141"
      },
      {
        "rank": 18,
        "name": "ブルー Temple Slivered ブーツカット ジーンズ",
        "brand": "Rick Owens DRKSHDW",
        "price": "¥202,500",
        "image": "https://res.cloudinary.com/ssenseweb/image/upload/__IMAGE_PARAMS__/261126M186005_1.jpg",
        "url": "https://www.ssense.com/ja-jp/men/product/19098591"
      },
      {
        "rank": 19,
        "name": "ブラック Multi Charms スタッズ ベルト",
        "brand": "Vivienne Westwood",
        "price": "¥77,500",
        "image": "https://res.cloudinary.com/ssenseweb/image/upload/__IMAGE_PARAMS__/261314M131026_1.jpg",
        "url": "https://www.ssense.com/ja-jp/men/product/18971021"
      },
      {
        "rank": 20,
        "name": "オレンジ＆カーキ フリース＆グログラン ジャケット",
        "brand": "sacai",
        "price": "¥95,000",
        "image": "https://res.cloudinary.com/ssenseweb/image/upload/__IMAGE_PARAMS__/252445M180004_1.jpg",
        "url": "https://www.ssense.com/ja-jp/men/product/18169771"
      }
    ]
  },
  "farfetch": {
    "source": "farfetch.com",
    "count": 20,
    "items": [
      {
        "rank": 1,
        "name": "paint-splatter denim jacket",
        "brand": "MM6 Maison Margiela",
        "price": "￥132,000",
        "image": "https://cdn-images.farfetch-contents.com/36/00/88/94/36008894_67813340_480.jpg",
        "url": "https://www.farfetch.com/jp/shopping/men/mm6-maison-margiela-paint-splatter-denim-jacket-item-36008894.aspx"
      },
      {
        "rank": 2,
        "name": "nubuck-leather shoulder bag",
        "brand": "Prada",
        "price": "￥550,000",
        "image": "https://cdn-images.farfetch-contents.com/36/08/30/97/36083097_67708443_480.jpg",
        "url": "https://www.farfetch.com/jp/shopping/men/prada-nubuck-leather-shoulder-bag-item-36083097.aspx"
      },
      {
        "rank": 3,
        "name": "T-Boxt-N14 Tシャツ",
        "brand": "Diesel",
        "price": "￥16,500",
        "image": "https://cdn-images.farfetch-contents.com/35/69/63/79/35696379_67480488_480.jpg",
        "url": "https://www.farfetch.com/jp/shopping/men/diesel-t-boxt-n14-t-item-35696379.aspx"
      },
      {
        "rank": 4,
        "name": "エナメルレザー＆テクニカルファブリック America's Cup スニーカー",
        "brand": "Prada",
        "price": "￥151,800",
        "image": "https://cdn-images.farfetch-contents.com/35/98/93/26/35989326_67602536_480.jpg",
        "url": "https://www.farfetch.com/jp/shopping/men/prada-americas-cup-item-35989326.aspx"
      },
      {
        "rank": 5,
        "name": "エッセンシャルロゴ刺しゅうジャケット",
        "brand": "FEAR OF GOD ESSENTIALS",
        "price": "￥50,500",
        "image": "https://cdn-images.farfetch-contents.com/35/85/04/46/35850446_67445262_480.jpg",
        "url": "https://www.farfetch.com/jp/shopping/men/fear-of-god-essentials--item-35850446.aspx"
      },
      {
        "rank": 6,
        "name": "2001 D-Macro relaxed-fit distressed-details denim jeans",
        "brand": "Diesel",
        "price": "￥39,600",
        "image": "https://cdn-images.farfetch-contents.com/35/77/54/83/35775483_67676879_480.jpg",
        "url": "https://www.farfetch.com/jp/shopping/men/diesel-2001-d-macro-relaxed-fit-distressed-details-denim-jeans-item-35775483.aspx"
      },
      {
        "rank": 7,
        "name": "striped button-down shirt",
        "brand": "Polo Ralph Lauren",
        "price": "￥25,200",
        "image": "https://cdn-images.farfetch-contents.com/36/12/81/08/36128108_67756705_480.jpg",
        "url": "https://www.farfetch.com/jp/shopping/men/polo-ralph-lauren-striped-button-down-shirt-item-36128108.aspx"
      },
      {
        "rank": 8,
        "name": "cat-eye sunglasses",
        "brand": "Diesel",
        "price": "￥47,000",
        "image": "https://cdn-images.farfetch-contents.com/36/12/85/53/36128553_67782705_480.jpg",
        "url": "https://www.farfetch.com/jp/shopping/women/diesel-cat-eye-sunglasses-item-36128553.aspx"
      },
      {
        "rank": 9,
        "name": "floral-print hoodie",
        "brand": "Wooyoungmi",
        "price": "￥114,400",
        "image": "https://cdn-images.farfetch-contents.com/36/13/86/65/36138665_67762111_480.jpg",
        "url": "https://www.farfetch.com/jp/shopping/men/wooyoungmi-floral-print-hoodie-item-36138665.aspx"
      },
      {
        "rank": 10,
        "name": "medium FF Fendi Lui shoulder bag",
        "brand": "FENDI",
        "price": "￥374,400",
        "image": "https://cdn-images.farfetch-contents.com/36/12/19/11/36121911_67754943_480.jpg",
        "url": "https://www.farfetch.com/jp/shopping/men/fendi-medium-ff-fendi-lui-shoulder-bag-item-36121911.aspx"
      },
      {
        "rank": 11,
        "name": "Essenza バックパック",
        "brand": "Dolce & Gabbana",
        "price": "￥385,000",
        "image": "https://cdn-images.farfetch-contents.com/35/85/30/51/35853051_67591988_480.jpg",
        "url": "https://www.farfetch.com/jp/shopping/men/dolce-gabbana-essenza-item-35853051.aspx"
      },
      {
        "rank": 12,
        "name": "contrast-stitch bermuda shorts",
        "brand": "FENDI",
        "price": "￥146,200",
        "image": "https://cdn-images.farfetch-contents.com/36/10/83/75/36108375_67755926_480.jpg",
        "url": "https://www.farfetch.com/jp/shopping/men/fendi-contrast-stitch-bermuda-shorts-item-36108375.aspx"
      },
      {
        "rank": 13,
        "name": "マヨリカ キャンバス ポルトフィーノ スニーカー",
        "brand": "Dolce & Gabbana",
        "price": "￥122,400",
        "image": "",
        "url": "https://www.farfetch.com/jp/shopping/men/dolce-gabbana--item-34814252.aspx"
      },
      {
        "rank": 14,
        "name": "アンティーブ ショッピングバッグ M",
        "brand": "Valentino Garavani",
        "price": "￥347,600",
        "image": "",
        "url": "https://www.farfetch.com/jp/shopping/men/valentino-garavani-m-item-34831854.aspx"
      },
      {
        "rank": 15,
        "name": "Vロゴ ポロシャツ",
        "brand": "Valentino Garavani",
        "price": "￥242,000",
        "image": "",
        "url": "https://www.farfetch.com/jp/shopping/men/valentino-garavani-v-item-35656812.aspx"
      },
      {
        "rank": 16,
        "name": "Gz ステッチディテール スニーカー",
        "brand": "Giuseppe Zanotti",
        "price": "￥88,000",
        "image": "",
        "url": "https://www.farfetch.com/jp/shopping/men/giuseppe-zanotti-gz-item-34480681.aspx"
      },
      {
        "rank": 17,
        "name": "トラックパンツ",
        "brand": "Billionaire",
        "price": "￥108,300",
        "image": "",
        "url": "https://www.farfetch.com/jp/shopping/men/billionaire--item-32462624.aspx"
      },
      {
        "rank": 18,
        "name": "multi-pocket press-stud jacket",
        "brand": "Loro Piana",
        "price": "￥811,100",
        "image": "",
        "url": "https://www.farfetch.com/jp/shopping/men/loro-piana-multi-pocket-press-stud-jacket-item-35738065.aspx"
      },
      {
        "rank": 19,
        "name": "Orb-plaque crossbody bag",
        "brand": "Vivienne Westwood",
        "price": "￥59,300",
        "image": "",
        "url": "https://www.farfetch.com/jp/shopping/men/vivienne-westwood-orb-plaque-crossbody-bag-item-36112343.aspx"
      },
      {
        "rank": 20,
        "name": "striped panelled shirt",
        "brand": "Junya Watanabe MAN",
        "price": "￥173,000",
        "image": "",
        "url": "https://www.farfetch.com/jp/shopping/men/junya-watanabe-man-striped-panelled-shirt-item-35981970.aspx"
      }
    ]
  },
  "snkrdunk_sneakers": {
    "source": "snkrdunk.com",
    "count": 20,
    "items": [
      {
        "rank": 1,
        "name": "Supreme × Nike Air Force 1 Low \"White\"",
        "price": "¥19,298",
        "image": "https://cdn.snkrdunk.com/upload_bg_removed/20200302130137-1.webp?size=m",
        "url": "https://snkrdunk.com/products/CU9225-100"
      },
      {
        "rank": 2,
        "name": "New Balance 2010 \"Wasabi\" (atmos Japan Exclusive)",
        "price": "¥30,889",
        "image": "https://cdn.snkrdunk.com/upload_bg_removed/17fee6a9-72e5-4fc6-a629-e1dec7518b2a.webp?size=m",
        "url": "https://snkrdunk.com/products/U20105K7"
      },
      {
        "rank": 3,
        "name": "Nike Air Max 95 Big Bubble \"Slate\"",
        "price": "¥25,400",
        "image": "https://cdn.snkrdunk.com/upload_bg_removed/ca999d48-3f7c-4ee7-bac1-93e14c3e5377.webp?size=m",
        "url": "https://snkrdunk.com/products/IH7855-100"
      },
      {
        "rank": 4,
        "name": "Nike Air Max 95 OG Big Bubble \"Neon Yellow\" (2025/2026)",
        "price": "¥27,299",
        "image": "https://cdn.snkrdunk.com/upload_bg_removed/20250320071217-0.webp?size=m",
        "url": "https://snkrdunk.com/products/HM4740-001"
      },
      {
        "rank": 5,
        "name": "Nike Air Force 1 Low '07 \"White/White\"",
        "price": "¥12,999",
        "image": "https://cdn.snkrdunk.com/upload_bg_removed/20250601024911-0.webp?size=m",
        "url": "https://snkrdunk.com/products/CW2288-111"
      },
      {
        "rank": 6,
        "name": "Nike Hyperdunk 2017 Low \"Pink Foam/Black\"",
        "price": "¥11,957",
        "image": "https://cdn.snkrdunk.com/upload_bg_removed/20251009060540-0.webp?size=m",
        "url": "https://snkrdunk.com/products/IM3368-606"
      },
      {
        "rank": 7,
        "name": "New Balance 1906L \"Black Suede\"",
        "price": "¥13,403",
        "image": "https://cdn.snkrdunk.com/upload_bg_removed/20250212033628-0.webp?size=m",
        "url": "https://snkrdunk.com/products/U1906LNT"
      },
      {
        "rank": 8,
        "name": "fragment design × UNION × Nike Air Jordan 1 High OG \"Black/Varsity Red\"",
        "price": "¥30,088",
        "image": "https://cdn.snkrdunk.com/upload_bg_removed/20260218012248-0.webp?size=m",
        "url": "https://snkrdunk.com/products/IO7847-002"
      },
      {
        "rank": 9,
        "name": "New Balance 1906L \"Rich Oak Suede\"",
        "price": "¥12,253",
        "image": "https://cdn.snkrdunk.com/upload_bg_removed/20250212033628-1.webp?size=m",
        "url": "https://snkrdunk.com/products/U1906LNS"
      },
      {
        "rank": 10,
        "name": "Nike Women's Cortez \"Polka Dot/Black/White\"",
        "price": "¥15,480",
        "image": "https://cdn.snkrdunk.com/upload_bg_removed/e97980e8-24fe-43c2-a018-1870d017a27a.webp?size=m",
        "url": "https://snkrdunk.com/products/IR1332-001"
      },
      {
        "rank": 11,
        "name": "Nike Air Max 95 OG Big Bubble PRM \"Comet\"",
        "price": "¥25,000",
        "image": "https://cdn.snkrdunk.com/upload_bg_removed/04bd4e68-bdfe-437b-ba14-8d8d7c06ff89.webp?size=m",
        "url": "https://snkrdunk.com/products/IB7862-100"
      },
      {
        "rank": 12,
        "name": "atmos × POINTLESS JOURNEY (King Gnu Daiki Tsuneta) × Superstar 2 \"DGH Solid Grey\"",
        "price": "¥40,000",
        "image": "https://cdn.snkrdunk.com/upload_bg_removed/d8c474bc-2d0a-41cc-9b41-ee63ad1d4636.webp?size=m",
        "url": "https://snkrdunk.com/products/KJ8846"
      },
      {
        "rank": 13,
        "name": "atmos × POINTLESS JOURNEY (King Gnu Daiki Tsuneta) × Superstar 2 \"Clear Onix\"",
        "price": "¥38,000",
        "image": "https://cdn.snkrdunk.com/upload_bg_removed/7d66265f-8ca0-45de-a977-4de9448d6273.webp?size=m",
        "url": "https://snkrdunk.com/products/KJ8847"
      },
      {
        "rank": 14,
        "name": "Supreme × Nike Air Force 1 Low \"Black\"",
        "price": "¥19,400",
        "image": "https://cdn.snkrdunk.com/upload_bg_removed/20210902041113-0.webp?size=m",
        "url": "https://snkrdunk.com/products/CU9225-001"
      },
      {
        "rank": 15,
        "name": "Nike Air Jordan 1 Low Golf \"Chicago\"",
        "price": "¥24,798",
        "image": "https://cdn.snkrdunk.com/upload_bg_removed/f23e3892-cea1-4ac2-95f5-01e820b60c5a.webp?size=m",
        "url": "https://snkrdunk.com/products/IQ3417-600"
      },
      {
        "rank": 16,
        "name": "Nike Air Liquid Max \"Triple Black\"",
        "price": "¥31,900",
        "image": "https://cdn.snkrdunk.com/upload_bg_removed/d0e4807a-38aa-47ff-8cbd-52143dac0787.webp?size=m",
        "url": "https://snkrdunk.com/products/IQ7634-003"
      },
      {
        "rank": 17,
        "name": "Palace Skateboards × Nike Air Max 95 Big Bubble \"Metallic Silver/Aluminum\"",
        "price": "¥28,799",
        "image": "https://cdn.snkrdunk.com/upload_bg_removed/baa8533b-9ccc-4322-ae36-f76c40a5632e.webp?size=m",
        "url": "https://snkrdunk.com/products/IQ7708-095"
      },
      {
        "rank": 18,
        "name": "New Balance 9060 Summer \"Black\"",
        "price": "¥19,900",
        "image": "https://cdn.snkrdunk.com/upload_bg_removed/b4664c4a-37d1-44a1-a9ed-1de5a7de742a.webp?size=m",
        "url": "https://snkrdunk.com/products/U90604SC"
      },
      {
        "rank": 19,
        "name": "Nike SB Air Force 1 Low \"Light Orewood Brown/Pink Foam\"",
        "price": "¥16,500",
        "image": "https://cdn.snkrdunk.com/upload_bg_removed/20260126012440-0.webp?size=m",
        "url": "https://snkrdunk.com/products/HM8517-100"
      },
      {
        "rank": 20,
        "name": "Nike Air Max 95 OG Big Bubble \"Granite\" (2026)",
        "price": "¥20,498",
        "image": "https://cdn.snkrdunk.com/upload_bg_removed/20260312010940-0.webp?size=m",
        "url": "https://snkrdunk.com/products/HM4740-007"
      }
    ]
  },
  "snkrdunk_apparel": {
    "source": "snkrdunk.com",
    "count": 20,
    "items": [
      {
        "rank": 1,
        "name": "Arcade REX by ChroNoiR \\ Vampire Heart by Kuzuha S/S T-shirt \"BLACK\"",
        "price": "¥6,600",
        "image": "https://cdn.snkrdunk.com/upload_bg_removed/7615c881-9ef6-4044-bb57-c671a9ec8750.webp?size=m",
        "url": "https://snkrdunk.com/apparels/783020/primary?navigation=jsShowAndHideAppBar"
      },
      {
        "rank": 2,
        "name": "Arcade REX by ChroNoiR \\ Angel Heart by Kanae S/S T-shirt \"WHITE\"",
        "price": "¥6,600",
        "image": "https://cdn.snkrdunk.com/upload_bg_removed/4bac21bf-2e82-4be3-9370-1e22bfa24481.webp?size=m",
        "url": "https://snkrdunk.com/apparels/783017/primary?navigation=jsShowAndHideAppBar"
      },
      {
        "rank": 3,
        "name": "武尊 引退記念 \\ TAKERU “武尊” Tee by WAYP MUSIC \"SUMIKURO\"",
        "price": "",
        "image": "https://cdn.snkrdunk.com/upload_bg_removed/ee37c9a3-bfa1-44fe-9dfe-13310a0e55d3.webp?size=m",
        "url": "https://snkrdunk.com/apparels/784056"
      },
      {
        "rank": 4,
        "name": "Arcade REX by ChroNoiR \\ Arcade Logo Baseball Cap \"BLACK\"",
        "price": "¥5,500",
        "image": "https://cdn.snkrdunk.com/upload_bg_removed/ff609d66-4210-4bd5-80d2-a02e4d0200df.webp?size=m",
        "url": "https://snkrdunk.com/apparels/783023/primary?navigation=jsShowAndHideAppBar"
      },
      {
        "rank": 5,
        "name": "WTAPS T-6M 03 / Cap / Ctpl. Twill \"Black\"",
        "price": "¥14,789",
        "image": "https://cdn.snkrdunk.com/upload_bg_removed/42c3f2ca-62fd-47ae-9ea0-74f2e644513c.webp?size=m",
        "url": "https://snkrdunk.com/apparels/815233"
      },
      {
        "rank": 6,
        "name": "武尊 引退記念 \\ TAKERU STICKER SET \"MULTI\"",
        "price": "",
        "image": "https://cdn.snkrdunk.com/upload_bg_removed/bd6cbdf6-6e3f-497f-962e-da03e04798c8.webp?size=m",
        "url": "https://snkrdunk.com/apparels/784061"
      },
      {
        "rank": 7,
        "name": "Arcade REX by ChroNoiR \\ Arcade REX Key Visual S/S T-SHIRT \"BLACK\"",
        "price": "¥7,000",
        "image": "https://cdn.snkrdunk.com/upload_bg_removed/92fd210e-aadd-4292-9ccb-50fe56d9e6ef.webp?size=m",
        "url": "https://snkrdunk.com/apparels/783022/primary?navigation=jsShowAndHideAppBar"
      },
      {
        "rank": 8,
        "name": "COMME des GARCONS PLAY CDG AX-T242-051 \"White\"",
        "price": "¥13,999",
        "image": "https://cdn.snkrdunk.com/uploads/media/20250805063942-0.png?size=m",
        "url": "https://snkrdunk.com/apparels/384511"
      },
      {
        "rank": 9,
        "name": "Supreme x Hanes Spider-Man Boxer Briefs (2 Pack) \"Black\"",
        "price": "¥7,900",
        "image": "https://cdn.snkrdunk.com/upload_bg_removed/SUP-SS26-WEEK9-001-2.webp?size=m",
        "url": "https://snkrdunk.com/apparels/811922"
      },
      {
        "rank": 10,
        "name": "Nike Jordan x FRAGMENT x UNION Tee \"White\"",
        "price": "¥8,400",
        "image": "https://cdn.snkrdunk.com/upload_bg_removed/20260305054720-0.webp?size=m",
        "url": "https://snkrdunk.com/apparels/763097"
      },
      {
        "rank": 11,
        "name": "Supreme x Hanes Spider-Man Tagless Tees (2 Pack) \"Black\"",
        "price": "¥7,799",
        "image": "https://cdn.snkrdunk.com/upload_bg_removed/SUP-SS26-WEEK9-005-2.webp?size=m",
        "url": "https://snkrdunk.com/apparels/811936"
      },
      {
        "rank": 12,
        "name": "Supreme x Hanes Spider-Man Boxer Briefs (2 Pack) \"Red\"",
        "price": "¥10,798",
        "image": "https://cdn.snkrdunk.com/upload_bg_removed/SUP-SS26-WEEK9-001-1.webp?size=m",
        "url": "https://snkrdunk.com/apparels/811921"
      },
      {
        "rank": 13,
        "name": "LEVI'S Vintage Clothing S506XX 1944 Jacket \"Indigo\"",
        "price": "¥79,000",
        "image": "https://cdn.snkrdunk.com/upload_bg_removed/20250808053008-0.webp?size=m",
        "url": "https://snkrdunk.com/apparels/656121"
      },
      {
        "rank": 14,
        "name": "Supreme x Hanes Spider-Man Tagless Tees (2 Pack) \"Red\"",
        "price": "¥8,899",
        "image": "https://cdn.snkrdunk.com/upload_bg_removed/SUP-SS26-WEEK9-005-1.webp?size=m",
        "url": "https://snkrdunk.com/apparels/811935"
      },
      {
        "rank": 15,
        "name": "Supreme x MM6 Maison Margiela Box Logo Zip Up Hooded Sweatshirt \"Black\"",
        "price": "¥84,700",
        "image": "https://cdn.snkrdunk.com/upload_bg_removed/ac64dc36-688e-4c00-abfc-46cbf1ddeb70.webp?size=m",
        "url": "https://snkrdunk.com/apparels/781175"
      },
      {
        "rank": 16,
        "name": "Supreme x Hanes Spider-Man Boxer Briefs (2 Pack) \"White\"",
        "price": "¥8,000",
        "image": "https://cdn.snkrdunk.com/upload_bg_removed/SUP-SS26-WEEK9-001.webp?size=m",
        "url": "https://snkrdunk.com/apparels/811920"
      },
      {
        "rank": 17,
        "name": "Supreme Satin Applique Sweatpant \"Black\"",
        "price": "¥32,998",
        "image": "https://cdn.snkrdunk.com/upload_bg_removed/502f31e3-7116-4c31-9316-9147dedd3b88.webp?size=m",
        "url": "https://snkrdunk.com/apparels/811943"
      },
      {
        "rank": 18,
        "name": "Supreme Raffia Mesh Back 5-Panel \"Black\"",
        "price": "¥11,860",
        "image": "https://cdn.snkrdunk.com/upload_bg_removed/SUP-SS26-WEEK9-012-1.webp?size=m",
        "url": "https://snkrdunk.com/apparels/811951"
      },
      {
        "rank": 19,
        "name": "Supreme x MM6 Maison Margiela Split S/S Top \"Black\"",
        "price": "¥26,399",
        "image": "https://cdn.snkrdunk.com/upload_bg_removed/c8a8a936-d99e-440d-8480-b2cec55a8078.webp?size=m",
        "url": "https://snkrdunk.com/apparels/781187"
      },
      {
        "rank": 20,
        "name": "Supreme Raffia Mesh Back 5-Panel \"Tan\"",
        "price": "¥15,569",
        "image": "https://cdn.snkrdunk.com/upload_bg_removed/64c30905-1d6f-466d-98d2-43022584af9f.webp?size=m",
        "url": "https://snkrdunk.com/apparels/811950"
      }
    ]
  }
}